logging_config/__init__.py
atman_logging_config-0.1.dist-info/METADATA
atman_logging_config-0.1.dist-info/WHEEL
atman_logging_config-0.1.dist-info/top_level.txt
atman_logging_config-0.1.dist-info/RECORD
